pyrosenv/__init__.py
pyrosenv/cv_bridge/__init__.py
pyrosenv/genpy/__init__.py
pyrosenv/rosbag/__init__.py
pyrosenv/rosgraph/__init__.py
pyrosenv/roslaunch/__init__.py
pyrosenv/roslib/__init__.py
pyrosenv/rosnode/__init__.py
pyrosenv/rospy/__init__.py
pyrosenv/sensor_msgs/__init__.py
pyrosenv/sensor_msgs/point_cloud2.py
pyrosenv/sensor_msgs/msg/__init__.py
pyrosenv/std_msgs/__init__.py
pyrosenv/std_msgs/msg/__init__.py
pyrosenv-0.0.4.dist-info/LICENSE
pyrosenv-0.0.4.dist-info/METADATA
pyrosenv-0.0.4.dist-info/WHEEL
pyrosenv-0.0.4.dist-info/top_level.txt
pyrosenv-0.0.4.dist-info/RECORD
