Metadata-Version: 2.1
Name: pyrosenv
Version: 0.0.4
Summary: Set an environment for easy work with ROS in python without setting things up
Home-page: https://github.com/omrirz/pyrosenv.git
Author: Omri Rozenzaft
Author-email: omrirz@gmail.com
License: UNKNOWN
Platform: UNKNOWN
Classifier: Programming Language :: Python
Classifier: Programming Language :: Python :: 3.6
Classifier: Programming Language :: Python :: 3.7
Classifier: Programming Language :: Python :: 3.8
Classifier: Programming Language :: Python :: 3 :: Only
Classifier: License :: OSI Approved :: MIT License
Classifier: Operating System :: Unix
Requires-Python: >=3.6
Requires-Dist: pyros-setup
Requires-Dist: rospkg
Requires-Dist: defusedxml
Requires-Dist: pycrypto
Requires-Dist: gnupg
